ceph_client/__init__.py
ceph_client/main.py
ceph_client-1.0.3.dist-info/METADATA
ceph_client-1.0.3.dist-info/WHEEL
ceph_client-1.0.3.dist-info/RECORD
