Metadata-Version: 2.3
Name: ceph-client
Version: 1.0.3
Summary: A Python client for Ceph S3-compatible storage
Author: Your Name
Author-email: your.email@example.com
Requires-Python: >=3.12,<4.0
Classifier: Programming Language :: Python :: 3
Classifier: Programming Language :: Python :: 3.12
Classifier: Programming Language :: Python :: 3.13
Requires-Dist: boto3 (>=1.34.0,<2.0.0)
Requires-Dist: loguru (>=0.7.2,<0.8.0)
